spectralbridges/__init__.py
spectral_bridges-1.3.0.dist-info/LICENSE.txt
spectral_bridges-1.3.0.dist-info/METADATA
spectral_bridges-1.3.0.dist-info/WHEEL
spectral_bridges-1.3.0.dist-info/top_level.txt
spectral_bridges-1.3.0.dist-info/RECORD
