Metadata-Version: 2.1
Name: spectral-bridges
Version: 1.3.0
Summary: Spectral Bridges clustering algorithm
Home-page: https://github.com/felixlaplante/spectral-bridges-pypi/
Author: Félix Laplante
Author-email: flheight0@gmail.com
Classifier: Programming Language :: Python :: 3
Classifier: License :: OSI Approved :: MIT License
Classifier: Operating System :: MacOS :: MacOS X
Classifier: Operating System :: Microsoft :: Windows
Classifier: Operating System :: POSIX :: Linux
Requires-Python: >=3.8
License-File: LICENSE.txt
Requires-Dist: numpy
Requires-Dist: scipy
Requires-Dist: faiss-cpu
